pybitshred/__init__.py
pybitshred/binary_file.py
pybitshred/bitshred.py
pybitshred/fingerprint.py
pybitshred/fingerprint_db.py
pybitshred/utils.py
pybitshred-0.1.2.dist-info/METADATA
pybitshred-0.1.2.dist-info/WHEEL
pybitshred-0.1.2.dist-info/entry_points.txt
pybitshred-0.1.2.dist-info/licenses/LICENSE
pybitshred-0.1.2.dist-info/RECORD
