Metadata-Version: 2.3
Name: pybitshred
Version: 0.1.2
Summary: A tool for large-scale malware similarity analysis and clustering
Project-URL: Homepage, https://github.com/jerry871002/pybitshred
Project-URL: Issues, https://github.com/jerry871002/pybitshred/issues
Author-email: Jerry Yang <jerry871002@gmail.com>
License-File: LICENSE
Classifier: License :: OSI Approved :: MIT License
Classifier: Operating System :: OS Independent
Classifier: Programming Language :: Python :: 3
Classifier: Programming Language :: Python :: 3.8
Classifier: Programming Language :: Python :: 3.9
Classifier: Programming Language :: Python :: 3.10
Classifier: Programming Language :: Python :: 3.11
Classifier: Topic :: Security
Requires-Python: >=3.8
Requires-Dist: pefile==2023.2.7
Requires-Dist: psutil==6.0.0
